crowdwiz/__init__.py
crowdwiz/account.py
crowdwiz/amount.py
crowdwiz/asset.py
crowdwiz/block.py
crowdwiz/blockchain.py
crowdwiz/blockchainobject.py
crowdwiz/committee.py
crowdwiz/crowdwiz.py
crowdwiz/dex.py
crowdwiz/exceptions.py
crowdwiz/genesisbalance.py
crowdwiz/htlc.py
crowdwiz/instance.py
crowdwiz/market.py
crowdwiz/memo.py
crowdwiz/message.py
crowdwiz/notify.py
crowdwiz/price.py
crowdwiz/proposal.py
crowdwiz/storage.py
crowdwiz/transactionbuilder.py
crowdwiz/utils.py
crowdwiz/vesting.py
crowdwiz/wallet.py
crowdwiz/witness.py
crowdwiz/worker.py
crowdwizapi/__init__.py
crowdwizapi/crowdwiznoderpc.py
crowdwizapi/exceptions.py
crowdwizapi/websocket.py
crowdwizbase/__init__.py
crowdwizbase/account.py
crowdwizbase/asset_permissions.py
crowdwizbase/bip38.py
crowdwizbase/chains.py
crowdwizbase/memo.py
crowdwizbase/objects.py
crowdwizbase/objecttypes.py
crowdwizbase/operationids.py
crowdwizbase/operations.py
crowdwizbase/signedtransactions.py
crowdwizbase/transactions.py
crowdwiz-0.9.4.dist-info/AUTHORS
crowdwiz-0.9.4.dist-info/LICENSE.txt
crowdwiz-0.9.4.dist-info/METADATA
crowdwiz-0.9.4.dist-info/WHEEL
crowdwiz-0.9.4.dist-info/top_level.txt
crowdwiz-0.9.4.dist-info/RECORD
