Metadata-Version: 2.1
Name: crowdwiz
Version: 0.9.4
Summary: Python library for crowdwiz
Home-page: https://github.com/crowdwiz-biz/python-crowdwiz
Author: Donbc Crowdwiz
Author-email: donbc@protonmail.com
Maintainer: Donbc Crowdwiz
Maintainer-email: donbc@protonmail.com
License: UNKNOWN
Download-URL: https://github.com/crowdwiz-biz/python-crowdwiz/tarball/0.9.4
Keywords: crowdwiz,library,api,rpc,cwd
Platform: UNKNOWN
Classifier: License :: OSI Approved :: MIT License
Classifier: Operating System :: OS Independent
Classifier: Programming Language :: Python :: 3
Classifier: Development Status :: 3 - Alpha
Classifier: Intended Audience :: Developers
Classifier: Intended Audience :: Financial and Insurance Industry
Classifier: Topic :: Office/Business :: Financial
Requires-Dist: Events (==0.3)
Requires-Dist: graphenelib (>=1.1.16)
Requires-Dist: websockets (>=7.0)
